_mblack_version.py
mblack/__init__.py
mblack/brackets.py
mblack/cache.py
mblack/comments.py
mblack/concurrency.py
mblack/const.py
mblack/debug.py
mblack/files.py
mblack/handle_ipynb_magics.py
mblack/linegen.py
mblack/lines.py
mblack/mode.py
mblack/nodes.py
mblack/numerics.py
mblack/output.py
mblack/parsing.py
mblack/report.py
mblack/rusty.py
mblack/strings.py
mblack/trans.py
mblib2to3/__init__.py
mblib2to3/pgen2/__init__.py
mblib2to3/pgen2/driver.py
mblib2to3/pgen2/grammar.py
mblib2to3/pgen2/literals.py
mblib2to3/pgen2/parse.py
mblib2to3/pgen2/pgen.py
mblib2to3/pgen2/token.py
mblib2to3/pgen2/tokenize.py
mblib2to3/pygram.py
mblib2to3/pytree.py
mblack-26.1.0.dist-info/WHEEL
mblack-26.1.0.dist-info/METADATA
mblack-26.1.0.dist-info/entry_points.txt
mblack-26.1.0.data/purelib/mblib2to3/Grammar.txt
mblack-26.1.0.data/purelib/mblib2to3/PatternGrammar.txt
mblack-26.1.0.dist-info/LICENSE
mblack-26.1.0.dist-info/RECORD
