Metadata-Version: 2.1
Name: mblack
Author: Modular Inc
Author-email: hello@modular.com
Home-page: https://modular.com
License: LicenseRef-MAX-Platform-Software-License
Summary: The Mojo programming language formatter, forked from black
Requires-Dist: click>=8.0.0
Requires-Dist: mypy-extensions>=0.4.3
Requires-Dist: pathspec>=0.9.0
Requires-Dist: platformdirs>=2
Requires-Dist: tomli>=1.1.0; python_full_version < "3.11.0a7"
Version: 26.1.0
